httpsyncer/__init__.py
httpsyncer/core.py
httpsyncer/t.py
httpsyncer-1.0.0.dist-info/METADATA
httpsyncer-1.0.0.dist-info/WHEEL
httpsyncer-1.0.0.dist-info/top_level.txt
httpsyncer-1.0.0.dist-info/RECORD
